smoothnlp_api/__init__.py
smoothnlp_api/api_client.py
smoothnlp_api/configuration.py
smoothnlp_api/rest.py
smoothnlp_api/api/__init__.py
smoothnlp_api/api/company_api.py
smoothnlp_api/api/investment_api.py
smoothnlp_api/api/news_api.py
smoothnlp_api/models/__init__.py
smoothnlp_api-0.1.4.dist-info/LICENSE
smoothnlp_api-0.1.4.dist-info/METADATA
smoothnlp_api-0.1.4.dist-info/WHEEL
smoothnlp_api-0.1.4.dist-info/top_level.txt
smoothnlp_api-0.1.4.dist-info/RECORD
