Metadata-Version: 2.1
Name: smoothnlp-api
Version: 0.1.4
Summary: Investment
Home-page: https://github.com/smoothnlp/smoothnlp_api
Author-email: zhangruinan@smoothnlp.com
License: UNKNOWN
Keywords: Swagger,data,api
Platform: UNKNOWN
Requires-Dist: urllib3 (>=1.15)
Requires-Dist: six (>=1.10)
Requires-Dist: certifi
Requires-Dist: python-dateutil
